{
    "additionalUserInfo": {
        "isNewUser": true
    },
    "user": {
        "displayName": null,
        "email": "yadav@gmail.com",
        "emailVerified": false,
        "isAnonymous": false,
        "metadata": [Object
        ],
        "multiFactor": [Object
        ],
        "phoneNumber": null,
        "photoURL": null,
        "providerData": [Array
        ],
        "providerId": "firebase",
        "tenantId": null,
        "uid": "OCCTWosWkwMiQr16ZgjGHz5RZCp2"
    }
}



{
    "additionalUserInfo": {
        "isNewUser": false
    },
    "user": {
        "displayName": null,
        "email": "yadav@gmail.com",
        "emailVerified": false,
        "isAnonymous": false,
        "metadata": [Object
        ],
        "multiFactor": [Object
        ],
        "phoneNumber": null,
        "photoURL": null,
        "providerData": [Array
        ],
        "providerId": "firebase",
        "tenantId": null,
        "uid": "OCCTWosWkwMiQr16ZgjGHz5RZCp2"
    }
}